cfm_id/__init__.py
cfm_id/cfm_id.py
cfm_id/hash.py
cfm_id/matchms.py
cfm_id/settings.py
cfm_id-0.1.7.dist-info/entry_points.txt
cfm_id-0.1.7.dist-info/WHEEL
cfm_id-0.1.7.dist-info/METADATA
cfm_id-0.1.7.dist-info/RECORD
