Metadata-Version: 2.1
Name: cfm-id
Version: 0.1.7
Summary: A Python wrapper to use CFM-ID : https://cfmid.wishartlab.com
Home-page: https://gitlab.com/metwork/libs/cfm-id
License: LGPL-2.1-only
Author: Yann Beauxis
Author-email: dev@yannbeauxis.net
Requires-Python: >=3.7.1,<4.0.0
Classifier: License :: OSI Approved
Classifier: Programming Language :: Python :: 3
Classifier: Programming Language :: Python :: 3.10
Classifier: Programming Language :: Python :: 3.8
Classifier: Programming Language :: Python :: 3.9
Requires-Dist: llvmlite (>=0.34.0,<0.35.0)
Requires-Dist: matchms (>=0.13.0,<0.14.0)
Requires-Dist: pandas (>=1.3.4,<2.0.0)
Requires-Dist: pydantic (>=1.8.2,<2.0.0)
Project-URL: Repository, https://gitlab.com/metwork/libs/cfm-id
